{"metadata": {"dbt_schema_version": "https://schemas.getdbt.com/dbt/run-results/v4.json", "dbt_version": "1.5.4", "generated_at": "2023-09-18T05:32:44.105675Z", "invocation_id": "5aaa4c28-ef2a-4128-bfcb-92c58e6824b2", "env": {}}, "results": [{"status": "success", "timing": [{"name": "compile", "started_at": "2023-09-18T05:32:43.859769Z", "completed_at": "2023-09-18T05:32:43.870815Z"}, {"name": "execute", "started_at": "2023-09-18T05:32:43.872322Z", "completed_at": "2023-09-18T05:32:43.872343Z"}], "thread_id": "Thread-1 (worker)", "execution_time": 0.014555931091308594, "adapter_response": {}, "message": null, "failures": null, "unique_id": "seed.jaffle_shop.raw_customers"}, {"status": "success", "timing": [{"name": "compile", "started_at": "2023-09-18T05:32:43.876001Z", "completed_at": "2023-09-18T05:32:43.877168Z"}, {"name": "execute", "started_at": "2023-09-18T05:32:43.877947Z", "completed_at": "2023-09-18T05:32:43.877955Z"}], "thread_id": "Thread-1 (worker)", "execution_time": 0.0038728713989257812, "adapter_response": {}, "message": null, "failures": null, "unique_id": "seed.jaffle_shop.raw_orders"}, {"status": "success", "timing": [{"name": "compile", "started_at": "2023-09-18T05:32:43.880101Z", "completed_at": "2023-09-18T05:32:43.881225Z"}, {"name": "execute", "started_at": "2023-09-18T05:32:43.881911Z", "completed_at": "2023-09-18T05:32:43.881918Z"}], "thread_id": "Thread-1 (worker)", "execution_time": 0.0030918121337890625, "adapter_response": {}, "message": null, "failures": null, "unique_id": "seed.jaffle_shop.raw_payments"}, {"status": "success", "timing": [{"name": "compile", "started_at": "2023-09-18T05:32:43.884480Z", "completed_at": "2023-09-18T05:32:43.887271Z"}, {"name": "execute", "started_at": "2023-09-18T05:32:43.887973Z", "completed_at": "2023-09-18T05:32:43.887981Z"}], "thread_id": "Thread-1 (worker)", "execution_time": 0.004834175109863281, "adapter_response": {}, "message": null, "failures": null, "unique_id": "model.jaffle_shop.stg_customers"}, {"status": "success", "timing": [{"name": "compile", "started_at": "2023-09-18T05:32:43.890347Z", "completed_at": "2023-09-18T05:32:43.893321Z"}, {"name": "execute", "started_at": "2023-09-18T05:32:43.894085Z", "completed_at": "2023-09-18T05:32:43.894094Z"}], "thread_id": "Thread-1 (worker)", "execution_time": 0.005126953125, "adapter_response": {}, "message": null, "failures": null, "unique_id": "model.jaffle_shop.stg_orders"}, {"status": "success", "timing": [{"name": "compile", "started_at": "2023-09-18T05:32:43.897461Z", "completed_at": "2023-09-18T05:32:43.899693Z"}, {"name": "execute", "started_at": "2023-09-18T05:32:43.900309Z", "completed_at": "2023-09-18T05:32:43.900316Z"}], "thread_id": "Thread-1 (worker)", "execution_time": 0.0041294097900390625, "adapter_response": {}, "message": null, "failures": null, "unique_id": "model.jaffle_shop.stg_payments"}, {"status": "success", "timing": [{"name": "compile", "started_at": "2023-09-18T05:32:43.902410Z", "completed_at": "2023-09-18T05:32:43.911733Z"}, {"name": "execute", "started_at": "2023-09-18T05:32:43.912421Z", "completed_at": "2023-09-18T05:32:43.912428Z"}], "thread_id": "Thread-1 (worker)", "execution_time": 0.01132655143737793, "adapter_response": {}, "message": null, "failures": null, "unique_id": "test.jaffle_shop.not_null_stg_customers_customer_id.e2cfb1f9aa"}, {"status": "success", "timing": [{"name": "compile", "started_at": "2023-09-18T05:32:43.914867Z", "completed_at": "2023-09-18T05:32:43.920248Z"}, {"name": "execute", "started_at": "2023-09-18T05:32:43.920931Z", "completed_at": "2023-09-18T05:32:43.920939Z"}], "thread_id": "Thread-1 (worker)", "execution_time": 0.007415771484375, "adapter_response": {}, "message": null, "failures": null, "unique_id": "test.jaffle_shop.unique_stg_customers_customer_id.c7614daada"}, {"status": "success", "timing": [{"name": "compile", "started_at": "2023-09-18T05:32:43.923176Z", "completed_at": "2023-09-18T05:32:43.930879Z"}, {"name": "execute", "started_at": "2023-09-18T05:32:43.931544Z", "completed_at": "2023-09-18T05:32:43.931551Z"}], "thread_id": "Thread-1 (worker)", "execution_time": 0.009709358215332031, "adapter_response": {}, "message": null, "failures": null, "unique_id": "test.jaffle_shop.accepted_values_stg_orders_status__placed__shipped__completed__return_pending__returned.080fb20aad"}, {"status": "success", "timing": [{"name": "compile", "started_at": "2023-09-18T05:32:43.933574Z", "completed_at": "2023-09-18T05:32:43.936882Z"}, {"name": "execute", "started_at": "2023-09-18T05:32:43.937507Z", "completed_at": "2023-09-18T05:32:43.937513Z"}], "thread_id": "Thread-1 (worker)", "execution_time": 0.005212068557739258, "adapter_response": {}, "message": null, "failures": null, "unique_id": "test.jaffle_shop.not_null_stg_orders_order_id.81cfe2fe64"}, {"status": "success", "timing": [{"name": "compile", "started_at": "2023-09-18T05:32:43.939597Z", "completed_at": "2023-09-18T05:32:43.943216Z"}, {"name": "execute", "started_at": "2023-09-18T05:32:43.943851Z", "completed_at": "2023-09-18T05:32:43.943857Z"}], "thread_id": "Thread-1 (worker)", "execution_time": 0.005540370941162109, "adapter_response": {}, "message": null, "failures": null, "unique_id": "test.jaffle_shop.unique_stg_orders_order_id.e3b841c71a"}, {"status": "success", "timing": [{"name": "compile", "started_at": "2023-09-18T05:32:43.945801Z", "completed_at": "2023-09-18T05:32:43.948201Z"}, {"name": "execute", "started_at": "2023-09-18T05:32:43.948804Z", "completed_at": "2023-09-18T05:32:43.948809Z"}], "thread_id": "Thread-1 (worker)", "execution_time": 0.004209041595458984, "adapter_response": {}, "message": null, "failures": null, "unique_id": "model.jaffle_shop.customers"}, {"status": "success", "timing": [{"name": "compile", "started_at": "2023-09-18T05:32:43.951573Z", "completed_at": "2023-09-18T05:32:43.954888Z"}, {"name": "execute", "started_at": "2023-09-18T05:32:43.955571Z", "completed_at": "2023-09-18T05:32:43.955581Z"}], "thread_id": "Thread-1 (worker)", "execution_time": 0.0061342716217041016, "adapter_response": {}, "message": null, "failures": null, "unique_id": "model.jaffle_shop.orders"}, {"status": "success", "timing": [{"name": "compile", "started_at": "2023-09-18T05:32:43.957761Z", "completed_at": "2023-09-18T05:32:43.963143Z"}, {"name": "execute", "started_at": "2023-09-18T05:32:43.963768Z", "completed_at": "2023-09-18T05:32:43.963776Z"}], "thread_id": "Thread-1 (worker)", "execution_time": 0.007506847381591797, "adapter_response": {}, "message": null, "failures": null, "unique_id": "test.jaffle_shop.accepted_values_stg_payments_payment_method__credit_card__coupon__bank_transfer__gift_card.3c3820f278"}, {"status": "success", "timing": [{"name": "compile", "started_at": "2023-09-18T05:32:43.965858Z", "completed_at": "2023-09-18T05:32:43.969202Z"}, {"name": "execute", "started_at": "2023-09-18T05:32:43.969801Z", "completed_at": "2023-09-18T05:32:43.969807Z"}], "thread_id": "Thread-1 (worker)", "execution_time": 0.00522613525390625, "adapter_response": {}, "message": null, "failures": null, "unique_id": "test.jaffle_shop.not_null_stg_payments_payment_id.c19cc50075"}, {"status": "success", "timing": [{"name": "compile", "started_at": "2023-09-18T05:32:43.971783Z", "completed_at": "2023-09-18T05:32:43.975504Z"}, {"name": "execute", "started_at": "2023-09-18T05:32:43.976125Z", "completed_at": "2023-09-18T05:32:43.976131Z"}], "thread_id": "Thread-1 (worker)", "execution_time": 0.005570888519287109, "adapter_response": {}, "message": null, "failures": null, "unique_id": "test.jaffle_shop.unique_stg_payments_payment_id.3744510712"}, {"status": "success", "timing": [{"name": "compile", "started_at": "2023-09-18T05:32:43.978141Z", "completed_at": "2023-09-18T05:32:43.981491Z"}, {"name": "execute", "started_at": "2023-09-18T05:32:43.982116Z", "completed_at": "2023-09-18T05:32:43.982123Z"}], "thread_id": "Thread-1 (worker)", "execution_time": 0.005203962326049805, "adapter_response": {}, "message": null, "failures": null, "unique_id": "test.jaffle_shop.not_null_customers_customer_id.5c9bf9911d"}, {"status": "success", "timing": [{"name": "compile", "started_at": "2023-09-18T05:32:43.984013Z", "completed_at": "2023-09-18T05:32:43.987355Z"}, {"name": "execute", "started_at": "2023-09-18T05:32:43.988010Z", "completed_at": "2023-09-18T05:32:43.988016Z"}], "thread_id": "Thread-1 (worker)", "execution_time": 0.0052678585052490234, "adapter_response": {}, "message": null, "failures": null, "unique_id": "test.jaffle_shop.unique_customers_customer_id.c5af1ff4b1"}, {"status": "success", "timing": [{"name": "compile", "started_at": "2023-09-18T05:32:43.990202Z", "completed_at": "2023-09-18T05:32:43.995480Z"}, {"name": "execute", "started_at": "2023-09-18T05:32:43.996096Z", "completed_at": "2023-09-18T05:32:43.996103Z"}], "thread_id": "Thread-1 (worker)", "execution_time": 0.007216215133666992, "adapter_response": {}, "message": null, "failures": null, "unique_id": "test.jaffle_shop.accepted_values_orders_status__placed__shipped__completed__return_pending__returned.be6b5b5ec3"}, {"status": "success", "timing": [{"name": "compile", "started_at": "2023-09-18T05:32:43.998132Z", "completed_at": "2023-09-18T05:32:44.049501Z"}, {"name": "execute", "started_at": "2023-09-18T05:32:44.050203Z", "completed_at": "2023-09-18T05:32:44.050210Z"}], "thread_id": "Thread-1 (worker)", "execution_time": 0.0533292293548584, "adapter_response": {}, "message": null, "failures": null, "unique_id": "test.jaffle_shop.not_null_orders_amount.106140f9fd"}, {"status": "success", "timing": [{"name": "compile", "started_at": "2023-09-18T05:32:44.052234Z", "completed_at": "2023-09-18T05:32:44.056125Z"}, {"name": "execute", "started_at": "2023-09-18T05:32:44.056825Z", "completed_at": "2023-09-18T05:32:44.056832Z"}], "thread_id": "Thread-1 (worker)", "execution_time": 0.005977630615234375, "adapter_response": {}, "message": null, "failures": null, "unique_id": "test.jaffle_shop.not_null_orders_bank_transfer_amount.7743500c49"}, {"status": "success", "timing": [{"name": "compile", "started_at": "2023-09-18T05:32:44.059174Z", "completed_at": "2023-09-18T05:32:44.062796Z"}, {"name": "execute", "started_at": "2023-09-18T05:32:44.063426Z", "completed_at": "2023-09-18T05:32:44.063433Z"}], "thread_id": "Thread-1 (worker)", "execution_time": 0.005596160888671875, "adapter_response": {}, "message": null, "failures": null, "unique_id": "test.jaffle_shop.not_null_orders_coupon_amount.ab90c90625"}, {"status": "success", "timing": [{"name": "compile", "started_at": "2023-09-18T05:32:44.065406Z", "completed_at": "2023-09-18T05:32:44.068789Z"}, {"name": "execute", "started_at": "2023-09-18T05:32:44.069372Z", "completed_at": "2023-09-18T05:32:44.069379Z"}], "thread_id": "Thread-1 (worker)", "execution_time": 0.005285739898681641, "adapter_response": {}, "message": null, "failures": null, "unique_id": "test.jaffle_shop.not_null_orders_credit_card_amount.d3ca593b59"}, {"status": "success", "timing": [{"name": "compile", "started_at": "2023-09-18T05:32:44.071347Z", "completed_at": "2023-09-18T05:32:44.075253Z"}, {"name": "execute", "started_at": "2023-09-18T05:32:44.075879Z", "completed_at": "2023-09-18T05:32:44.075885Z"}], "thread_id": "Thread-1 (worker)", "execution_time": 0.005774497985839844, "adapter_response": {}, "message": null, "failures": null, "unique_id": "test.jaffle_shop.not_null_orders_customer_id.c5f02694af"}, {"status": "success", "timing": [{"name": "compile", "started_at": "2023-09-18T05:32:44.077910Z", "completed_at": "2023-09-18T05:32:44.081226Z"}, {"name": "execute", "started_at": "2023-09-18T05:32:44.081852Z", "completed_at": "2023-09-18T05:32:44.081859Z"}], "thread_id": "Thread-1 (worker)", "execution_time": 0.005138397216796875, "adapter_response": {}, "message": null, "failures": null, "unique_id": "test.jaffle_shop.not_null_orders_gift_card_amount.413a0d2d7a"}, {"status": "success", "timing": [{"name": "compile", "started_at": "2023-09-18T05:32:44.083745Z", "completed_at": "2023-09-18T05:32:44.087125Z"}, {"name": "execute", "started_at": "2023-09-18T05:32:44.087696Z", "completed_at": "2023-09-18T05:32:44.087702Z"}], "thread_id": "Thread-1 (worker)", "execution_time": 0.005204439163208008, "adapter_response": {}, "message": null, "failures": null, "unique_id": "test.jaffle_shop.not_null_orders_order_id.cf6c17daed"}, {"status": "success", "timing": [{"name": "compile", "started_at": "2023-09-18T05:32:44.089835Z", "completed_at": "2023-09-18T05:32:44.097050Z"}, {"name": "execute", "started_at": "2023-09-18T05:32:44.097794Z", "completed_at": "2023-09-18T05:32:44.097802Z"}], "thread_id": "Thread-1 (worker)", "execution_time": 0.009277820587158203, "adapter_response": {}, "message": null, "failures": null, "unique_id": "test.jaffle_shop.relationships_orders_customer_id__customer_id__ref_customers_.c6ec7f58f2"}, {"status": "success", "timing": [{"name": "compile", "started_at": "2023-09-18T05:32:44.099739Z", "completed_at": "2023-09-18T05:32:44.103057Z"}, {"name": "execute", "started_at": "2023-09-18T05:32:44.103696Z", "completed_at": "2023-09-18T05:32:44.103702Z"}], "thread_id": "Thread-1 (worker)", "execution_time": 0.005228281021118164, "adapter_response": {}, "message": null, "failures": null, "unique_id": "test.jaffle_shop.unique_orders_order_id.fed79b3a6e"}], "elapsed_time": 1.3270766735076904, "args": {"exclude": [], "cache_selected_only": false, "use_colors": true, "vars": {}, "indirect_selection": "eager", "quiet": false, "partial_parse": true, "static_parser": true, "warn_error_options": {"include": [], "exclude": []}, "defer": false, "log_level": "info", "populate_cache": true, "compile": true, "log_format_file": "debug", "strict_mode": false, "macro_debugging": false, "project_dir": "dags/dbt/jaffle_shop", "log_format": "default", "version_check": true, "send_anonymous_usage_stats": true, "printer_width": 80, "profiles_dir": "dags/dbt/jaffle_shop", "log_path": "dags/dbt/jaffle_shop/logs", "enable_legacy_logger": false, "log_level_file": "debug", "favor_state": false, "use_colors_file": true, "write_json": true, "print": true, "select": [], "introspect": true, "which": "generate"}}